{
  "wanderer-vessel-tshirt": {
    "id": "wanderer-vessel-tshirt",
    "name": "Wanderer Vessel",
    "price": 45.00,
    "description": "Ilustração original inspirada em viagens marítimas, 100% algodão orgânico.",
    "category": "T-shirt",
    "cardImage": "Website_Imgs/5.png",
    "url": "Product-mockup.html",
    "badge": "Novo",
    "images": {
      "mainImage": "Website_Imgs/tshirt.svg",
      "image2": "Website_Imgs/tshirtback-01.svg",
      "image3": "Website_Imgs/tshirt3-01.svg",
      "image4": "Website_Imgs/tshirt2.svg"
    }
  },
  "urban-explorer-tshirt": {
    "id": "urban-explorer-tshirt",
    "name": "Urban Explorer",
    "price": 60.00,
    "description": "Design urbano e contemporâneo, tecido premium 100% algodão orgânico.",
    "category": "T-shirt",
    "cardImage": "Website_Imgs/6.png",
    "url": "Product.html?nome=urban-explorer-tshirt",
    "badge": null,
    "images": {
      "mainImage": "Website_Imgs/6.png",
      "image2": "Website_Imgs/6.png",
      "image3": "Website_Imgs/6.png",
      "image4": "Website_Imgs/6.png"
    }
  },
  "minimal-essence": {
    "id": "minimal-essence",
    "name": "Minimal Essence",
    "price": 25.00,
    "description": "Minimalismo aplicado ao design de moda, corte regular unissexo.",
    "category": "T-shirt",
    "cardImage": "Website_Imgs/6.png",
    "url": "Product.html?nome=minimal-essence",
    "badge": null,
    "images": {
      "mainImage": "Website_Imgs/6.png",
      "image2": "Website_Imgs/6.png",
      "image3": "Website_Imgs/6.png",
      "image4": "Website_Imgs/6.png"
    }
  }
}
